pyciosa/__init__.py
pyciosa/periodo.py
pyciosa-0.0.5.dist-info/METADATA
pyciosa-0.0.5.dist-info/WHEEL
pyciosa-0.0.5.dist-info/top_level.txt
pyciosa-0.0.5.dist-info/RECORD
