Metadata-Version: 2.1
Name: pyciosa
Version: 0.0.5
Summary: common utilities for new projects
Home-page: https://github.com/marco-gallegos/pyciosa.git
Author: Marco A. Gallegos
Author-email: ma_galeza@hotmail.com
License: UNKNOWN
Platform: UNKNOWN
Classifier: Programming Language :: Python :: 3
Classifier: License :: OSI Approved :: MIT License
Classifier: Operating System :: OS Independent
Requires-Python: >=3.6
Requires-Dist: numpy
Requires-Dist: pendulum
